ckanext/__init__.py
ckanext/wirecloud_view/__init__.py
ckanext/wirecloud_view/controller.py
ckanext/wirecloud_view/plugin.py
ckanext/wirecloud_view/fanstatic/wirecloud_option.js
ckanext/wirecloud_view/fanstatic/wirecloud_view.css
ckanext/wirecloud_view/templates/wirecloud_form.html
ckanext/wirecloud_view/templates/wirecloud_view.html
ckanext/wirecloud_view/tests/__init__.py
ckanext/wirecloud_view/tests/test_controller.py
ckanext/wirecloud_view/tests/test_plugin.py
ckanext_wirecloud_view-1.1.0.dist-info/METADATA
ckanext_wirecloud_view-1.1.0.dist-info/RECORD
ckanext_wirecloud_view-1.1.0.dist-info/WHEEL
ckanext_wirecloud_view-1.1.0.dist-info/entry_points.txt
ckanext_wirecloud_view-1.1.0.dist-info/top_level.txt
