Metadata-Version: 2.1
Name: ckanext-wirecloud-view
Version: 1.1.0
Summary: Provide visualization dashboards on CKAN using WireCloud
Home-page: https://github.com/conwetlab/ckanext-wirecloud_view
Author: CoNWeT Lab
Author-email: wirecloud@conwet.com
License: AGPLv3+
Keywords: CKAN dashboard data visualization WireCloud
Platform: UNKNOWN
Classifier: Development Status :: 5 - Production/Stable
Classifier: License :: OSI Approved :: GNU Affero General Public License v3 or later (AGPLv3+)
Classifier: Operating System :: OS Independent
Classifier: Programming Language :: Python :: 2.6
Classifier: Programming Language :: Python :: 2.7
Requires-Dist: ckanext-oauth2 (>=0.4.0)
Requires-Dist: six
